{
    "docstring": "\"\"\"\n    Add (or update) the \"Vary\" header in the given HttpResponse object.\n    newheaders is a list of header names that should be in \"Vary\". If headers\n    contains an asterisk, then \"Vary\" header will consist of a single asterisk\n    '*'. Otherwise, existing headers in \"Vary\" aren't removed.\n    \"\"\"",
    "name": "patch_vary_headers",
    "namespace": "django.utils.cache.patch_vary_headers",
    "class_name": "",
    "module_name": "django.utils.cache",
    "package_name": ""
}