{
    "namespace": "django.core.management.commands.squashmigrations",
    "docstring": "",
    "classes": [
        {
            "docstring": "",
            "name": "Command",
            "namespace": "django.core.management.commands.squashmigrations.Command",
            "methods": [
                {
                    "docstring": "",
                    "name": "add_arguments",
                    "namespace": "django.core.management.commands.squashmigrations.Command.add_arguments",
                    "class_name": "django.core.management.commands.squashmigrations.Command",
                    "module_name": "",
                    "package_name": ""
                },
                {
                    "docstring": "",
                    "name": "handle",
                    "namespace": "django.core.management.commands.squashmigrations.Command.handle",
                    "class_name": "django.core.management.commands.squashmigrations.Command",
                    "module_name": "",
                    "package_name": ""
                },
                {
                    "docstring": "",
                    "name": "find_migration",
                    "namespace": "django.core.management.commands.squashmigrations.Command.find_migration",
                    "class_name": "django.core.management.commands.squashmigrations.Command",
                    "module_name": "",
                    "package_name": ""
                }
            ]
        }
    ],
    "functions": [],
    "package_name": "django.core.management.commands"
}