{
    "namespace": "django.core.checks.registry",
    "docstring": "",
    "classes": [
        {
            "docstring": "\"\"\"\n    Built-in tags for internal checks.\n    \"\"\"",
            "name": "Tags",
            "namespace": "django.core.checks.registry.Tags",
            "methods": []
        },
        {
            "docstring": "",
            "name": "CheckRegistry",
            "namespace": "django.core.checks.registry.CheckRegistry",
            "methods": [
                {
                    "docstring": "",
                    "name": "__init__",
                    "namespace": "django.core.checks.registry.CheckRegistry.__init__",
                    "class_name": "",
                    "module_name": "",
                    "package_name": ""
                },
                {
                    "docstring": "\"\"\"\n        Can be used as a function or a decorator. Register given function\n        `f` labeled with given `tags`. The function should receive **kwargs\n        and return list of Errors and Warnings.\n\n        Example::\n\n            registry = CheckRegistry()\n            @registry.register('mytag', 'anothertag')\n            def my_check(app_configs, **kwargs):\n                # ... perform checks and collect `errors` ...\n                return errors\n            # or\n            registry.register(my_check, 'mytag', 'anothertag')\n        \"\"\"",
                    "name": "register",
                    "namespace": "django.core.checks.registry.CheckRegistry.register",
                    "class_name": "",
                    "module_name": "",
                    "package_name": ""
                },
                {
                    "docstring": "\"\"\"\n        Run all registered checks and return list of Errors and Warnings.\n        \"\"\"",
                    "name": "run_checks",
                    "namespace": "django.core.checks.registry.CheckRegistry.run_checks",
                    "class_name": "",
                    "module_name": "",
                    "package_name": ""
                },
                {
                    "docstring": "",
                    "name": "tag_exists",
                    "namespace": "django.core.checks.registry.CheckRegistry.tag_exists",
                    "class_name": "",
                    "module_name": "",
                    "package_name": ""
                },
                {
                    "docstring": "",
                    "name": "tags_available",
                    "namespace": "django.core.checks.registry.CheckRegistry.tags_available",
                    "class_name": "",
                    "module_name": "",
                    "package_name": ""
                },
                {
                    "docstring": "",
                    "name": "get_checks",
                    "namespace": "django.core.checks.registry.CheckRegistry.get_checks",
                    "class_name": "",
                    "module_name": "",
                    "package_name": ""
                }
            ]
        }
    ],
    "functions": [],
    "package_name": "django.core.checks"
}