{
    "docstring": "",
    "namespace": "django.contrib.auth.mixins",
    "classes": [
        {
            "docstring": "\"\"\"\n    Abstract CBV mixin that gives access mixins the same customizable\n    functionality.\n    \"\"\"",
            "name": "AccessMixin",
            "parent_name": "django.contrib.auth.mixins"
        },
        {
            "docstring": "\"\"\"Verify that the current user is authenticated.\"\"\"",
            "name": "LoginRequiredMixin",
            "parent_name": "django.contrib.auth.mixins"
        },
        {
            "docstring": "\"\"\"Verify that the current user has all specified permissions.\"\"\"",
            "name": "PermissionRequiredMixin",
            "parent_name": "django.contrib.auth.mixins"
        },
        {
            "docstring": "\"\"\"\n    Deny a request with a permission error if the test_func() method returns\n    False.\n    \"\"\"",
            "name": "UserPassesTestMixin",
            "parent_name": "django.contrib.auth.mixins"
        }
    ]
}