{
    "namespace": "django.contrib.redirects.models",
    "docstring": "",
    "classes": [
        {
            "docstring": "",
            "name": "Redirect",
            "namespace": "django.contrib.redirects.models.Redirect",
            "methods": [
                {
                    "docstring": "",
                    "name": "__str__",
                    "namespace": "django.contrib.redirects.models.Redirect.__str__",
                    "class_name": "django.contrib.redirects.models.Redirect",
                    "module_name": "",
                    "package_name": ""
                }
            ]
        }
    ],
    "functions": [],
    "package_name": "django.contrib.redirects"
}