{
    "docstring": "\"\"\"\n This module houses the ctypes initialization procedures, as well\n as the notice and error handler function callbacks (get called\n when an error occurs in GEOS).\n\n This module also houses GEOS Pointer utilities, including\n get_pointer_arr(), and GEOM_PTR.\n\"\"\"",
    "namespace": "django.contrib.gis.geos.libgeos",
    "classes": [
        {
            "docstring": "",
            "name": "GEOSGeom_t",
            "parent_name": "django.contrib.gis.geos.libgeos"
        },
        {
            "docstring": "",
            "name": "GEOSPrepGeom_t",
            "parent_name": "django.contrib.gis.geos.libgeos"
        },
        {
            "docstring": "",
            "name": "GEOSCoordSeq_t",
            "parent_name": "django.contrib.gis.geos.libgeos"
        },
        {
            "docstring": "",
            "name": "GEOSContextHandle_t",
            "parent_name": "django.contrib.gis.geos.libgeos"
        },
        {
            "docstring": "\"\"\"\n    Lazy loading of GEOS functions.\n    \"\"\"",
            "name": "GEOSFuncFactory",
            "parent_name": "django.contrib.gis.geos.libgeos"
        }
    ]
}