{
    "namespace": "django.contrib.gis.geos.prototypes.io",
    "docstring": "",
    "classes": [
        {
            "docstring": "",
            "name": "WKTReader_st",
            "namespace": "django.contrib.gis.geos.prototypes.io.WKTReader_st"
        },
        {
            "docstring": "",
            "name": "WKTWriter_st",
            "namespace": "django.contrib.gis.geos.prototypes.io.WKTWriter_st"
        },
        {
            "docstring": "",
            "name": "WKBReader_st",
            "namespace": "django.contrib.gis.geos.prototypes.io.WKBReader_st"
        },
        {
            "docstring": "",
            "name": "WKBWriter_st",
            "namespace": "django.contrib.gis.geos.prototypes.io.WKBWriter_st"
        },
        {
            "docstring": "",
            "name": "WKBReadFunc",
            "namespace": "django.contrib.gis.geos.prototypes.io.WKBReadFunc"
        },
        {
            "docstring": "",
            "name": "WKBWriteFunc",
            "namespace": "django.contrib.gis.geos.prototypes.io.WKBWriteFunc"
        },
        {
            "docstring": "",
            "name": "WKBWriterGet",
            "namespace": "django.contrib.gis.geos.prototypes.io.WKBWriterGet"
        },
        {
            "docstring": "",
            "name": "WKBWriterSet",
            "namespace": "django.contrib.gis.geos.prototypes.io.WKBWriterSet"
        },
        {
            "docstring": "\"Base class for GEOS I/O objects.\"",
            "name": "IOBase",
            "namespace": "django.contrib.gis.geos.prototypes.io.IOBase"
        },
        {
            "docstring": "",
            "name": "_WKTReader",
            "namespace": "django.contrib.gis.geos.prototypes.io._WKTReader"
        },
        {
            "docstring": "",
            "name": "_WKBReader",
            "namespace": "django.contrib.gis.geos.prototypes.io._WKBReader"
        },
        {
            "docstring": "",
            "name": "WKTWriter",
            "namespace": "django.contrib.gis.geos.prototypes.io.WKTWriter"
        },
        {
            "docstring": "",
            "name": "WKBWriter",
            "namespace": "django.contrib.gis.geos.prototypes.io.WKBWriter"
        },
        {
            "docstring": "",
            "name": "ThreadLocalIO",
            "namespace": "django.contrib.gis.geos.prototypes.io.ThreadLocalIO"
        }
    ]
}