{
    "name": "django.contrib.postgres.fields",
    "docstring": "",
    "package_name": "django.contrib.postgres",
    "classes": [],
    "modules": [
        {
            "namespace": "django.contrib.postgres.fields.citext",
            "docstring": "",
            "package_name": "django.contrib.postgres.fields"
        },
        {
            "namespace": "django.contrib.postgres.fields.ranges",
            "docstring": "",
            "package_name": "django.contrib.postgres.fields"
        },
        {
            "namespace": "django.contrib.postgres.fields.utils",
            "docstring": "",
            "package_name": "django.contrib.postgres.fields"
        },
        {
            "namespace": "django.contrib.postgres.fields.jsonb",
            "docstring": "",
            "package_name": "django.contrib.postgres.fields"
        },
        {
            "namespace": "django.contrib.postgres.fields.array",
            "docstring": "",
            "package_name": "django.contrib.postgres.fields"
        },
        {
            "namespace": "django.contrib.postgres.fields.hstore",
            "docstring": "",
            "package_name": "django.contrib.postgres.fields"
        }
    ],
    "subpackages": []
}