{
    "docstring": "\"\"\"\n    A JavaScript lexer\n\n    >>> lexer = JsLexer()\n    >>> list(lexer.lex(\"a = 1\"))\n    [('id', 'a'), ('ws', ' '), ('punct', '='), ('ws', ' '), ('dnum', '1')]\n\n    This doesn't properly handle non-ASCII characters in the JavaScript source.\n    \"\"\"",
    "name": "JsLexer",
    "namespace": "django.utils.jslex.JsLexer",
    "module_name": "django.utils.jslex",
    "package_name": "",
    "methods": [
        {
            "docstring": "",
            "name": "__init__",
            "namespace": "django.utils.jslex.JsLexer.__init__",
            "class_name": "django.utils.jslex.JsLexer",
            "module_name": "",
            "package_name": ""
        }
    ]
}