{
    "docstring": "",
    "name": "IncludeNode",
    "namespace": "django.template.loader_tags.IncludeNode",
    "module_name": "django.template.loader_tags",
    "package_name": "",
    "methods": [
        {
            "docstring": "",
            "name": "__init__",
            "namespace": "django.template.loader_tags.IncludeNode.__init__",
            "class_name": "django.template.loader_tags.IncludeNode",
            "module_name": "",
            "package_name": ""
        },
        {
            "docstring": "",
            "name": "__repr__",
            "namespace": "django.template.loader_tags.IncludeNode.__repr__",
            "class_name": "django.template.loader_tags.IncludeNode",
            "module_name": "",
            "package_name": ""
        },
        {
            "docstring": "\"\"\"\n        Render the specified template and context. Cache the template object\n        in render_context to avoid reparsing and loading when used in a for\n        loop.\n        \"\"\"",
            "name": "render",
            "namespace": "django.template.loader_tags.IncludeNode.render",
            "class_name": "django.template.loader_tags.IncludeNode",
            "module_name": "",
            "package_name": ""
        }
    ]
}