{
    "docstring": "",
    "name": "BtreeGinExtension",
    "namespace": "django.contrib.postgres.operations.BtreeGinExtension",
    "module_name": "django.contrib.postgres.operations",
    "package_name": "",
    "methods": [
        {
            "docstring": "",
            "name": "__init__",
            "namespace": "django.contrib.postgres.operations.BtreeGinExtension.__init__",
            "class_name": "django.contrib.postgres.operations.BtreeGinExtension",
            "module_name": "",
            "package_name": ""
        }
    ]
}