{
    "docstring": "",
    "name": "ContentTypesConfig",
    "namespace": "django.contrib.contenttypes.apps.ContentTypesConfig",
    "module_name": "django.contrib.contenttypes.apps",
    "package_name": "",
    "methods": [
        {
            "docstring": "",
            "name": "ready",
            "namespace": "django.contrib.contenttypes.apps.ContentTypesConfig.ready",
            "class_name": "django.contrib.contenttypes.apps.ContentTypesConfig",
            "module_name": "",
            "package_name": ""
        }
    ]
}