{
    "docstring": "\"\"\"Hold a reference to a foreign key name.\"\"\"",
    "name": "ForeignKeyName",
    "namespace": "django.db.backends.ddl_references.ForeignKeyName",
    "module_name": "django.db.backends.ddl_references",
    "package_name": "",
    "methods": [
        {
            "docstring": "",
            "name": "__init__",
            "namespace": "django.db.backends.ddl_references.ForeignKeyName.__init__",
            "class_name": "",
            "module_name": "",
            "package_name": ""
        },
        {
            "docstring": "",
            "name": "references_table",
            "namespace": "django.db.backends.ddl_references.ForeignKeyName.references_table",
            "class_name": "",
            "module_name": "",
            "package_name": ""
        },
        {
            "docstring": "",
            "name": "references_column",
            "namespace": "django.db.backends.ddl_references.ForeignKeyName.references_column",
            "class_name": "",
            "module_name": "",
            "package_name": ""
        },
        {
            "docstring": "",
            "name": "rename_table_references",
            "namespace": "django.db.backends.ddl_references.ForeignKeyName.rename_table_references",
            "class_name": "",
            "module_name": "",
            "package_name": ""
        },
        {
            "docstring": "",
            "name": "rename_column_references",
            "namespace": "django.db.backends.ddl_references.ForeignKeyName.rename_column_references",
            "class_name": "",
            "module_name": "",
            "package_name": ""
        },
        {
            "docstring": "",
            "name": "__str__",
            "namespace": "django.db.backends.ddl_references.ForeignKeyName.__str__",
            "class_name": "",
            "module_name": "",
            "package_name": ""
        }
    ]
}