{
    "docstring": "\"For coordinate sequence operations.\"",
    "name": "CsOperation",
    "namespace": "django.contrib.gis.geos.prototypes.coordseq.CsOperation",
    "module_name": "django.contrib.gis.geos.prototypes.coordseq",
    "package_name": "",
    "methods": [
        {
            "docstring": "",
            "name": "__init__",
            "namespace": "django.contrib.gis.geos.prototypes.coordseq.CsOperation.__init__",
            "class_name": "django.contrib.gis.geos.prototypes.coordseq.CsOperation",
            "module_name": "",
            "package_name": ""
        }
    ]
}