{
    "docstring": "\"\"\"An implementation of a cache binding using pymemcache.\"\"\"",
    "name": "PyMemcacheCache",
    "namespace": "django.core.cache.backends.memcached.PyMemcacheCache",
    "module_name": "django.core.cache.backends.memcached",
    "package_name": "",
    "methods": [
        {
            "docstring": "",
            "name": "__init__",
            "namespace": "django.core.cache.backends.memcached.PyMemcacheCache.__init__",
            "class_name": "",
            "module_name": "",
            "package_name": ""
        }
    ]
}